gap/pkg/cddinterface/LICENSE
gap/pkg/cddinterface/PackageInfo.g
gap/pkg/cddinterface/README.md
gap/pkg/cddinterface/ToDo.txt
gap/pkg/cddinterface/init.g
gap/pkg/cddinterface/install.sh
gap/pkg/cddinterface/makedoc.g
gap/pkg/cddinterface/read.g
gap/pkg/cddinterface/bin/aarch64-unknown-linux-gnu-default64-kv10/CddInterface.so
gap/pkg/cddinterface/etc/download.sh
gap/pkg/cddinterface/examples/30x30.g
gap/pkg/cddinterface/examples/FourierProjection.g
gap/pkg/cddinterface/examples/comparing_polyhedrons.g
gap/pkg/cddinterface/examples/demo.g
gap/pkg/cddinterface/examples/example1.g
gap/pkg/cddinterface/examples/intersection.g
gap/pkg/cddinterface/examples/linear_programs.g
gap/pkg/cddinterface/examples/minkuwski.g
gap/pkg/cddinterface/examples/new.g
gap/pkg/cddinterface/examples/new2.g
gap/pkg/cddinterface/gap/Julia.gd
gap/pkg/cddinterface/gap/Julia.gi
gap/pkg/cddinterface/gap/polyhedra.gd
gap/pkg/cddinterface/gap/polyhedra.gi
gap/pkg/cddinterface/gap/tools.gd
gap/pkg/cddinterface/gap/tools.gi
gap/pkg/cddinterface/tst/01.tst
gap/pkg/cddinterface/tst/02.tst
gap/pkg/cddinterface/tst/03.tst
gap/pkg/cddinterface/tst/04.tst
gap/pkg/cddinterface/tst/05.tst
gap/pkg/cddinterface/tst/06.tst
gap/pkg/cddinterface/tst/07.tst
gap/pkg/cddinterface/tst/08.tst
gap/pkg/cddinterface/tst/09.tst
gap/pkg/cddinterface/tst/10.tst
gap/pkg/cddinterface/tst/11.tst
gap/pkg/cddinterface/tst/etest_1.tst
gap/pkg/cddinterface/tst/etest_2.tst
gap/pkg/cddinterface/tst/testall.g
passagemath_gap_pkg_cddinterface/__init__.py
passagemath_gap_pkg_cddinterface.libs/libcddgmp-ac579979.so.0.1.3
passagemath_gap_pkg_cddinterface.libs/libgmp-93ebf16a.so.10.5.0
sage/all__sagemath_gap_pkg_cddinterface.py
sage/libs/all__sagemath_gap_pkg_cddinterface.py
sage/libs/gap_pkg_cddinterface.cpython-310-aarch64-linux-gnu.so
passagemath_gap_pkg_cddinterface-10.6.43.dist-info/METADATA
passagemath_gap_pkg_cddinterface-10.6.43.dist-info/METADATA.bak
passagemath_gap_pkg_cddinterface-10.6.43.dist-info/WHEEL
passagemath_gap_pkg_cddinterface-10.6.43.dist-info/top_level.txt
passagemath_gap_pkg_cddinterface-10.6.43.dist-info/RECORD
